LICENSE.txt
MANIFEST.in
README.md
setup.py
jk_infodatatree/DictTextMessage.py
jk_infodatatree/DictValue.py
jk_infodatatree/__init__.py
jk_infodatatree/flex.py
jk_infodatatree/jinja2_mediawiki_support.py
jk_infodatatree/mediawiki_support.py
jk_infodatatree/value_generation.py
jk_infodatatree/value_output_formatting.py
jk_infodatatree.egg-info/PKG-INFO
jk_infodatatree.egg-info/SOURCES.txt
jk_infodatatree.egg-info/dependency_links.txt
jk_infodatatree.egg-info/not-zip-safe
jk_infodatatree.egg-info/requires.txt
jk_infodatatree.egg-info/top_level.txt
jk_infodatatree/chk/AlertMessage.py
jk_infodatatree/chk/__init__.py
jk_infodatatree/chk/tree_value_checking.py