Metadata-Version: 2.1
Name: jk-infodatatree
Version: 0.2020.4.6
Summary: This python module provides support for creating and processing trees with informational data values. These data trees structure various values such as text strings, classic numerical values, values with units, timestamps and other kinds of values in a specific hierachical way. These can then be transformed and analysed e.g. to produce overview or detailed output.
Home-page: https://github.com/jkpubsrc/python-module-jk-infodatatree
Author: Jürgen Knauth
Author-email: pubsrc@binary-overflow.de
License: Apache 2.0
Download-URL: https://github.com/jkpubsrc/python-module-jk-infodatatree/tarball/0.2020.4.6
Keywords: json,data,jinja2
Platform: UNKNOWN
Classifier: Development Status :: 3 - Alpha
Classifier: License :: OSI Approved :: Apache Software License
